owl_dev/__init__.py
owl_dev/logging.py
owl_dev/database/__init__.py
owl_dev/database/model.py
owl_pipeline_develop-0.3.0.dist-info/METADATA
owl_pipeline_develop-0.3.0.dist-info/WHEEL
owl_pipeline_develop-0.3.0.dist-info/top_level.txt
owl_pipeline_develop-0.3.0.dist-info/RECORD
